textual_grounder/AppLogPanel.py
textual_grounder/GroundInfoPanel.py
textual_grounder/GroundSelectScreen.py
textual_grounder/JSApi.py
textual_grounder/RequestLogger.py
textual_grounder/Theme.py
textual_grounder/TokenGetter.py
textual_grounder/UserInfoPanel.py
textual_grounder/Verification.py
textual_grounder/__init__.py
textual_grounder/app.py
textual_grounder/app.spec
textual_grounder/grounder.css
textual_grounder/assets/grounder.ico
textual_grounder/assets/grounder.png
textual_grounder/assets/mitmdump.exe
textual_grounder/assets/trace.json
textual_grounder/assets/type__1754.js
textual_grounder/widgets/Header.py
textual_grounder/widgets/Table.py
textual_grounder/widgets/TimeSelect.py
textual_grounder/widgets/__init__.py
textual_grounder-0.0.2.dist-info/METADATA
textual_grounder-0.0.2.dist-info/WHEEL
textual_grounder-0.0.2.dist-info/entry_points.txt
textual_grounder-0.0.2.dist-info/RECORD
