Metadata-Version: 2.4
Name: textual-grounder
Version: 0.0.2
Summary: an app to order grounds in JiuShi Sports
Project-URL: Documentation, https://github.com/XIGUAjuice/textual-grounder#readme
Project-URL: Issues, https://github.com/XIGUAjuice/textual-grounder/issues
Project-URL: Source, https://github.com/XIGUAjuice/textual-grounder
Author-email: XIGUAjuice <xgjuice@qq.com>
License-Expression: MIT
Classifier: Development Status :: 4 - Beta
Classifier: Programming Language :: Python
Classifier: Programming Language :: Python :: 3.8
Classifier: Programming Language :: Python :: 3.9
Classifier: Programming Language :: Python :: 3.10
Classifier: Programming Language :: Python :: 3.11
Classifier: Programming Language :: Python :: 3.12
Classifier: Programming Language :: Python :: 3.13
Classifier: Programming Language :: Python :: Implementation :: CPython
Classifier: Programming Language :: Python :: Implementation :: PyPy
Requires-Python: >=3.8
Requires-Dist: httpx>=0.28.1
Requires-Dist: mitmproxy>=12.2.0
Requires-Dist: pycryptodome>=3.23.0
Requires-Dist: pynput>=1.8.1
Requires-Dist: pythonmonkey>=1.3.0
Requires-Dist: selenium>=4.37.0
Requires-Dist: textual
